zc/relation/README.rst
zc/relation/__init__.py
zc/relation/catalog.py
zc/relation/interfaces.py
zc/relation/optimization.rst
zc/relation/queryfactory.py
zc/relation/searchindex.py
zc/relation/searchindex.rst
zc/relation/tests.py
zc/relation/tokens.rst
zc/relation/timeit/manual_intersection.py
zc/relation/timeit/set_creation_vs_removal.py
zc/relation/timeit/transitive_search_index.py
zc_relation-3.0.dist-info/licenses/LICENSE.txt
zc_relation-3.0.dist-info/METADATA
zc_relation-3.0.dist-info/WHEEL
zc_relation-3.0.dist-info/top_level.txt
zc_relation-3.0.dist-info/RECORD
