Metadata-Version: 2.4
Name: zc.relation
Version: 3.0
Summary: Index intransitive and transitive n-ary relationships.
Home-page: https://github.com/zopefoundation/zc.relation
Author: Gary Poster
Author-email: zope-dev@zope.dev
License: ZPL-2.1
Keywords: zope zope3 relation
Classifier: Programming Language :: Python :: 3
Classifier: Programming Language :: Python :: 3.9
Classifier: Programming Language :: Python :: 3.10
Classifier: Programming Language :: Python :: 3.11
Classifier: Programming Language :: Python :: 3.12
Classifier: Programming Language :: Python :: 3.13
Classifier: Programming Language :: Python :: Implementation :: CPython
Classifier: License :: OSI Approved :: Zope Public License
Requires-Python: >=3.9
License-File: LICENSE.txt
Requires-Dist: BTrees
Requires-Dist: zope.interface
Requires-Dist: setuptools
Requires-Dist: zope.testing
Provides-Extra: test
Requires-Dist: zc.relationship>=2; extra == "test"
Requires-Dist: ZODB; extra == "test"
Dynamic: author
Dynamic: author-email
Dynamic: classifier
Dynamic: description
Dynamic: home-page
Dynamic: keywords
Dynamic: license
Dynamic: license-file
Dynamic: provides-extra
Dynamic: requires-dist
Dynamic: requires-python
Dynamic: summary
